spectrAOD/__init__.py
spectrAOD/batch_run.py
spectrAOD/format_data.py
spectrAOD/measure_aod.py
spectrAOD/mini_ions.csv
spectrAOD/spectrum_classes.py
spectrAOD/visualization.py
spectrAOD-1.1.0.dist-info/LICENSE.md
spectrAOD-1.1.0.dist-info/METADATA
spectrAOD-1.1.0.dist-info/WHEEL
spectrAOD-1.1.0.dist-info/entry_points.txt
spectrAOD-1.1.0.dist-info/top_level.txt
spectrAOD-1.1.0.dist-info/RECORD
