Metadata-Version: 2.1
Name: spectrAOD
Version: 1.1.0
Summary: This package is for measuring the apparent optical depth of spectra
Home-page: https://github.com/cmagness/spectrAOD
Author: Camellia Magness
Author-email: cmagness@stsci.edu
License: UNKNOWN
Keywords: astronomy
Platform: UNKNOWN
Classifier: Intended Audience :: Science/Research
Classifier: License :: OSI Approved :: BSD License
Classifier: Operating System :: OS Independent
Classifier: Programming Language :: Python
Classifier: Topic :: Scientific/Engineering :: Astronomy
Classifier: Topic :: Software Development :: Libraries :: Python Modules
Requires-Python: >=3.5
Requires-Dist: setuptools
Requires-Dist: numpy
Requires-Dist: astropy
Requires-Dist: pandas
Requires-Dist: argparse
Requires-Dist: pyyaml
